[
  {
    "id": "reel-67",
    "durationInSeconds": 16,
    "caption": "Unlock UK study success with AI-powered application strategies in 2026.",
    "audioUrl": "https://www.soundhelix.com/examples/mp3/SoundHelix-Song-1.mp3",
    "scenes": [
      {
        "text": "Dreaming of UK universities? AI tools boost your application odds.",
        "imageUrl": "https://images.unsplash.com/photo-1543269865-cbf427effbad?q=80&w=1080&h=1920&fit=crop"
      },
      {
        "text": "Scene 2: Personalised essay reviews and predictive success rates.",
        "imageUrl": "https://images.unsplash.com/photo-1551485645-e499a58eab2c?q=80&w=1080&h=1920&fit=crop"
      },
      {
        "text": "Contact Cohby Consult now for your AI edge.",
        "imageUrl": "https://images.unsplash.com/photo-1517486808906-6ca8b3f04846?q=80&w=1080&h=1920&fit=crop"
      }
    ]
  },
  {
    "id": "reel-68",
    "durationInSeconds": 16,
    "caption": "Canadian scholarships await. Master data-driven strategies.",
    "audioUrl": "https://www.soundhelix.com/examples/mp3/SoundHelix-Song-1.mp3",
    "scenes": [
      {
        "text": "Canada's top scholarships demand data analytics.",
        "imageUrl": "https://images.unsplash.com/photo-1494809610410-160faaed4de0?q=80&w=1080&h=1920&fit=crop"
      },
      {
        "text": "Scene 2: Use insights for standout profiles and funding matches.",
        "imageUrl": "https://images.unsplash.com/photo-1517486808906-6ca8b3f04846?q=80&w=1080&h=1920&fit=crop"
      },
      {
        "text": "Cohby Consult guides your data-powered win.",
        "imageUrl": "https://images.unsplash.com/photo-1585763465881-62c5d70627bc?q=80&w=1080&h=1920&fit=crop"
      }
    ]
  },
  {
    "id": "reel-69",
    "durationInSeconds": 16,
    "caption": "Europe study visas simplified with regulatory expertise.",
    "audioUrl": "https://www.soundhelix.com/examples/mp3/SoundHelix-Song-1.mp3",
    "scenes": [
      {
        "text": "Europe's visa rules tighten in 2026.",
        "imageUrl": "https://images.unsplash.com/photo-1517048676732-d65bc937f952?q=80&w=1080&h=1920&fit=crop"
      },
      {
        "text": "Scene 2: Expert compliance plans secure your approval.",
        "imageUrl": "https://images.unsplash.com/photo-1491975474562-1f4e30bc9468?q=80&w=1080&h=1920&fit=crop"
      },
      {
        "text": "Trust Cohby Consult for seamless entry.",
        "imageUrl": "https://images.unsplash.com/photo-1541339907198-e08756dedf3f?q=80&w=1080&h=1920&fit=crop"
      }
    ]
  },
  {
    "id": "reel-70",
    "durationInSeconds": 16,
    "caption": "Sustainability-focused UK programs. Your green path starts here.",
    "audioUrl": "https://www.soundhelix.com/examples/mp3/SoundHelix-Song-1.mp3",
    "scenes": [
      {
        "text": "UK unis prioritise ESG in admissions.",
        "imageUrl": "https://images.unsplash.com/photo-1531674842274-9563aa15686f?q=80&w=1080&h=1920&fit=crop"
      },
      {
        "text": "Scene 2: Build your sustainability profile with us.",
        "imageUrl": "https://images.unsplash.com/photo-1577643445874-a41763059685?q=80&w=1080&h=1920&fit=crop"
      },
      {
        "text": "Cohby Consult crafts your eco-advantage.",
        "imageUrl": "https://images.unsplash.com/photo-1577643445874-a41763059685?q=80&w=1080&h=1920&fit=crop"
      }
    ]
  },
  {
    "id": "reel-71",
    "durationInSeconds": 16,
    "caption": "Remote advising for Canadian dreams from anywhere.",
    "audioUrl": "https://www.soundhelix.com/examples/mp3/SoundHelix-Song-1.mp3",
    "scenes": [
      {
        "text": "Study Canada remotely with hybrid consulting.",
        "imageUrl": "https://images.unsplash.com/photo-1562349275-f5e7360af2dd?q=80&w=1080&h=1920&fit=crop"
      },
      {
        "text": "Scene 2: Flexible sessions fit your schedule.",
        "imageUrl": "https://images.unsplash.com/photo-1627556704263-b486db44a463?q=80&w=1080&h=1920&fit=crop"
      },
      {
        "text": "Join Cohby Consult's global team today.",
        "imageUrl": "https://images.unsplash.com/photo-1496317899792-9d7dbcd928a1?q=80&w=1080&h=1920&fit=crop"
      }
    ]
  },
  {
    "id": "reel-72",
    "durationInSeconds": 16,
    "caption": "Niche Europe masters. Specialise with our help.",
    "audioUrl": "https://www.soundhelix.com/examples/mp3/SoundHelix-Song-1.mp3",
    "scenes": [
      {
        "text": "Europe's niche programs in AI ethics call you.",
        "imageUrl": "https://images.unsplash.com/photo-1434030216411-0b793f4b4173?q=80&w=1080&h=1920&fit=crop"
      },
      {
        "text": "Scene 2: Tailored applications for specialised fields.",
        "imageUrl": "https://images.unsplash.com/photo-1693921398753-c5d114e8ae6a?q=80&w=1080&h=1920&fit=crop"
      },
      {
        "text": "Cohby Consult matches your unique skills.",
        "imageUrl": "https://images.unsplash.com/photo-1494809610410-160faaed4de0?q=80&w=1080&h=1920&fit=crop"
      }
    ]
  },
  {
    "id": "reel-73",
    "durationInSeconds": 16,
    "caption": "UK talent pipelines for competitive admissions.",
    "audioUrl": "https://www.soundhelix.com/examples/mp3/SoundHelix-Song-1.mp3",
    "scenes": [
      {
        "text": "UK unis seek diverse talent pipelines.",
        "imageUrl": "https://images.unsplash.com/photo-1563265500-fa2ff1f4fc9d?q=80&w=1080&h=1920&fit=crop"
      },
      {
        "text": "Scene 2: Skills-based prep beats degree focus.",
        "imageUrl": "https://images.unsplash.com/photo-1773332611476-6ec2ba68049f?q=80&w=1080&h=1920&fit=crop"
      },
      {
        "text": "Cohby Consult builds your standout profile.",
        "imageUrl": "https://images.unsplash.com/photo-1629348879298-d8fd280d8ee0?q=80&w=1080&h=1920&fit=crop"
      }
    ]
  },
  {
    "id": "reel-74",
    "durationInSeconds": 16,
    "caption": "Gig experts boost your Canada app game.",
    "audioUrl": "https://www.soundhelix.com/examples/mp3/SoundHelix-Song-1.mp3",
    "scenes": [
      {
        "text": "Fractional experts for Canada applications.",
        "imageUrl": "https://images.unsplash.com/photo-1494809610410-160faaed4de0?q=80&w=1080&h=1920&fit=crop"
      },
      {
        "text": "Scene 2: On-demand advice accelerates success.",
        "imageUrl": "https://images.unsplash.com/photo-1616428394230-ba242d33e3ba?q=80&w=1080&h=1920&fit=crop"
      },
      {
        "text": "Access Cohby Consult's network now.",
        "imageUrl": "https://images.unsplash.com/photo-1616428394230-ba242d33e3ba?q=80&w=1080&h=1920&fit=crop"
      }
    ]
  },
  {
    "id": "reel-75",
    "durationInSeconds": 16,
    "caption": "Geopolitical savvy for Europe study plans.",
    "audioUrl": "https://www.soundhelix.com/examples/mp3/SoundHelix-Song-1.mp3",
    "scenes": [
      {
        "text": "Europe's geopolitics impact study choices.",
        "imageUrl": "https://images.unsplash.com/photo-1519452635265-7b1fbfd1e4e0?q=80&w=1080&h=1920&fit=crop"
      },
      {
        "text": "Scene 2: Scenario planning secures your path.",
        "imageUrl": "https://images.unsplash.com/photo-1519452635265-7b1fbfd1e4e0?q=80&w=1080&h=1920&fit=crop"
      },
      {
        "text": "Cohby Consult navigates the shifts.",
        "imageUrl": "https://images.unsplash.com/photo-1558023784-f8343393cb06?q=80&w=1080&h=1920&fit=crop"
      }
    ]
  },
  {
    "id": "reel-76",
    "durationInSeconds": 16,
    "caption": "Tech accelerators in UK defence studies.",
    "audioUrl": "https://www.soundhelix.com/examples/mp3/SoundHelix-Song-1.mp3",
    "scenes": [
      {
        "text": "UK defence tech programs innovate fast.",
        "imageUrl": "https://images.unsplash.com/photo-1448584109583-8f5fe2e61544?q=80&w=1080&h=1920&fit=crop"
      },
      {
        "text": "Scene 2: Dual-use skills for future careers.",
        "imageUrl": "https://images.unsplash.com/photo-1773332585956-2d0e8ac80cb6?q=80&w=1080&h=1920&fit=crop"
      },
      {
        "text": "Cohby Consult positions you ahead.",
        "imageUrl": "https://images.unsplash.com/photo-1531674842274-9563aa15686f?q=80&w=1080&h=1920&fit=crop"
      }
    ]
  },
  {
    "id": "reel-77",
    "durationInSeconds": 16,
    "caption": "Canada's internal strategy groups need you.",
    "audioUrl": "https://www.soundhelix.com/examples/mp3/SoundHelix-Song-1.mp3",
    "scenes": [
      {
        "text": "Canadian firms grow internal strategy teams.",
        "imageUrl": "https://images.unsplash.com/photo-1541339907198-e08756dedf3f?q=80&w=1080&h=1920&fit=crop"
      },
      {
        "text": "Scene 2: Prep for in-house consulting roles.",
        "imageUrl": "https://images.unsplash.com/photo-1523240795612-9a054b0db644?q=80&w=1080&h=1920&fit=crop"
      },
      {
        "text": "Cohby Consult trains you for it.",
        "imageUrl": "https://images.unsplash.com/photo-1448584109583-8f5fe2e61544?q=80&w=1080&h=1920&fit=crop"
      }
    ]
  },
  {
    "id": "reel-78",
    "durationInSeconds": 16,
    "caption": "Multipolar innovation for Europe unis.",
    "audioUrl": "https://www.soundhelix.com/examples/mp3/SoundHelix-Song-1.mp3",
    "scenes": [
      {
        "text": "Europe scans global innovation hubs.",
        "imageUrl": "https://images.unsplash.com/photo-1558021211-6d1403321394?q=80&w=1080&h=1920&fit=crop"
      },
      {
        "text": "Scene 2: Broaden your research alliances.",
        "imageUrl": "https://images.unsplash.com/photo-1574100004472-e536d3b6bacc?q=80&w=1080&h=1920&fit=crop"
      },
      {
        "text": "Cohby Consult expands your horizons.",
        "imageUrl": "https://images.unsplash.com/photo-1551485645-e499a58eab2c?q=80&w=1080&h=1920&fit=crop"
      }
    ]
  },
  {
    "id": "reel-79",
    "durationInSeconds": 16,
    "caption": "UK just-in-time hiring trends for students.",
    "audioUrl": "https://www.soundhelix.com/examples/mp3/SoundHelix-Song-1.mp3",
    "scenes": [
      {
        "text": "UK firms ramp up quick hires in 2026.",
        "imageUrl": "https://images.unsplash.com/photo-1693921398753-c5d114e8ae6a?q=80&w=1080&h=1920&fit=crop"
      },
      {
        "text": "Scene 2: Agile skills for study-to-job transition.",
        "imageUrl": "https://images.unsplash.com/photo-1491975474562-1f4e30bc9468?q=80&w=1080&h=1920&fit=crop"
      },
      {
        "text": "Cohby Consult readies you fast.",
        "imageUrl": "https://images.unsplash.com/photo-1597920940566-a77511f9327d?q=80&w=1080&h=1920&fit=crop"
      }
    ]
  },
  {
    "id": "reel-80",
    "durationInSeconds": 16,
    "caption": "Predictive modelling for Canada acceptances.",
    "audioUrl": "https://www.soundhelix.com/examples/mp3/SoundHelix-Song-1.mp3",
    "scenes": [
      {
        "text": "Predict your Canada acceptance chances.",
        "imageUrl": "https://images.unsplash.com/photo-1604136514790-b27086f6c36e?q=80&w=1080&h=1920&fit=crop"
      },
      {
        "text": "Scene 2: Real-time insights optimise apps.",
        "imageUrl": "https://images.unsplash.com/photo-1681077375948-3df67cf1a95e?q=80&w=1080&h=1920&fit=crop"
      },
      {
        "text": "Start with Cohby Consult today.",
        "imageUrl": "https://images.unsplash.com/photo-1471974507711-fe913f4b4509?q=80&w=1080&h=1920&fit=crop"
      }
    ]
  }
]